pysikuli/__init__.py
pysikuli/_config.py
pysikuli/_main.py
pysikuli/_osx.py
pysikuli/_unix.py
pysikuli/_utils.py
pysikuli/_win.py
pysikuli/tools_data/_bleep.mp3
pysikuli/tools_data/_capture.mp3
pysikuli/tools_data/_finish.mp3
pysikuli-0.0.21.dist-info/LICENSE.txt
pysikuli-0.0.21.dist-info/METADATA
pysikuli-0.0.21.dist-info/WHEEL
pysikuli-0.0.21.dist-info/RECORD
