Metadata-Version: 2.1
Name: pysikuli
Version: 0.0.21
Summary: Fast cross-platform RPA tool for GUI automation
Home-page: https://github.com/OlegSmoliakov/pysikuli
License: LGPL-3.0-only
Keywords: gui,automation,desktop,RPA,test,testing,cross-platform,window,control,menu,title,name,geometry,size,position,move,resize,minimize,maximize,restore,hide,show,activate,raise,lower,close,screen-size,mouse-position,keyboard,mouse,cursor,click,press,keystroke,screen,screenshot,screencapture,screengrab,clipboard
Author: Oleg Smoliakov
Author-email: oleggsmolyakov@gmail.com
Requires-Python: >=3.10,<4.0
Classifier: Development Status :: 3 - Alpha
Classifier: License :: OSI Approved :: GNU General Public License v3 (GPLv3)
Classifier: License :: OSI Approved :: GNU Lesser General Public License v3 (LGPLv3)
Classifier: Operating System :: OS Independent
Classifier: Programming Language :: Python :: 3
Classifier: Programming Language :: Python :: 3.10
Classifier: Programming Language :: Python :: 3.11
Classifier: Programming Language :: Python :: 3.12
Classifier: Programming Language :: Python :: 3.13
Classifier: Topic :: Home Automation
Classifier: Topic :: Software Development :: Testing
Classifier: Topic :: Utilities
Requires-Dist: gitignore-parser (>=0.1.11,<0.2.0)
Requires-Dist: mss (>=9.0.1,<10.0.0)
Requires-Dist: numpy (>=1.26.4,<2.0.0)
Requires-Dist: opencv-python (==4.6.0.66)
Requires-Dist: pyhotkey (>=1.5.2,<2.0.0)
Requires-Dist: pymonctl (==0.7)
Requires-Dist: pymsgbox (>=1.0.9,<2.0.0)
Requires-Dist: pyperclip (>=1.8.2,<2.0.0)
Requires-Dist: pywinctl (>=0.3,<0.4)
Requires-Dist: send2trash (>=1.8.2,<2.0.0)
Requires-Dist: sounddevice (>=0.4.6,<0.5.0)
Requires-Dist: soundfile (>=0.12.1,<0.13.0)
Requires-Dist: wheel (>=0.42.0,<0.43.0)
Project-URL: Documentation, https://pysikuli.readthedocs.io
Project-URL: Repository, https://github.com/OlegSmoliakov/pysikuli
